rsmf/__init__.py
rsmf/abstract_formatter.py
rsmf/custom_formatter.py
rsmf/fontsizes.py
rsmf/quantumarticle.py
rsmf/revtex.py
rsmf/revtexlike.py
rsmf/setup.py
rsmf-0.2.1.dist-info/METADATA
rsmf-0.2.1.dist-info/WHEEL
rsmf-0.2.1.dist-info/top_level.txt
rsmf-0.2.1.dist-info/RECORD
