Metadata-Version: 2.1
Name: rsmf
Version: 0.2.1
Summary: rsmf (right-size my figures) helps you prepare publication-ready figures with matplotlib.
Home-page: https://github.com/johannesjmeyer/rsmf
Maintainer: Johannes Jakob Meyer
Maintainer-email: mail@johannesjakobmeyer.com
License: UNKNOWN
Platform: UNKNOWN
Classifier: Development Status :: 3 - Alpha
Classifier: Intended Audience :: Science/Research
Classifier: Programming Language :: Python :: 3
Provides: rsmf
Requires-Dist: matplotlib
